[
  {
    "list": [
      {
        "title": "Glitched Movie Player",
        "url"  : "/glitchedmovie/"
      },
      {
        "title": "Movie to Thumbnails",
        "url"  : "/movie2thumb/"
      },
      { "title": "Formant Khoomii",
        "url"  : "/khoomii/"
      },
      {
        "title": "Scalable Mario",
        "url"  : "/scalable-mario/"
      },
      {
        "title": "One Liner Music",
        "url"  : "/one-liner-music/"
      },
      {
        "title": "1bit Music",
        "url"  : "/1bit/"
      },
      {
        "title": "Endless Invention",
        "url"  : "/invention/"
      },
      {
        "title": "MiMi Grep",
        "url"  : "/mimi/"
      },
      {
        "title": "Perfume",
        "url"  : "/perfume/"
      },
      {
        "title": "Twitter Bot",
        "url"  : "/twitter-bot/"
      }
    ]
  },
  {
    "name": "libraries",
    "list": [
      {
        "title": "timbre.js",
        "url"  : "http://mohayonao.github.com/timbre.js"
      },
      {
        "title": "subcollider.js",
        "url"  : "http://mohayonao.github.com/subcollider.js"
      },
      {
        "title": "pico.js",
        "url"  : "https://github.com/mohayonao/pico.js"
      }
    ]
  },
  {
    "name": "accounts",
    "list": [
      {
        "title": "GitHub",
        "url"  : "https://github.com/mohayonao"
      },
      {
        "title": "Twitter",
        "url"  : "https://twitter.com/mohayonao"
      },
      {
        "title": "Hatena Blog",
        "url"  : "http://mohayonao.hatenablog.com/"
      }
    ]
  }
]
